grams/__init__.py
grams/grams.py
grams/hashtable.py
grams/linkedlist.py
grams/online.py
grams/stats.py
grams/termgraph.py
grams/utils.py
tests/__init__.py
tests/data.py
tests/test_data.py
tests/test_dictogram.py
tests/test_hashtable.py
tests/test_histogram.py
tests/test_linkedlist.py
tests/test_listogram.py
tests/test_online.py
tests/test_stats.py
tests/test_utils.py
grams-0.0.3.dist-info/LICENSE
grams-0.0.3.dist-info/METADATA
grams-0.0.3.dist-info/WHEEL
grams-0.0.3.dist-info/top_level.txt
grams-0.0.3.dist-info/RECORD
