Metadata-Version: 2.1
Name: grams
Version: 0.0.3
Summary: A package for managing histograms.
Home-page: https://github.com/escofresco/makeschool_fsp2_realtweets
Author: Jonasz Rice
Author-email: jonaszakr@gmail.com
License: UNKNOWN
Platform: UNKNOWN
Classifier: Programming Language :: Python :: 3
Classifier: License :: OSI Approved :: MIT License
Classifier: Operating System :: OS Independent
Requires-Python: >=3.7
Requires-Dist: numpy (==1.17.3)
Requires-Dist: dit (==1.2.3)
Requires-Dist: colorama (==0.4.1)
Requires-Dist: coverage (==4.5.4)
